README.md
setup.py
django_col/__init__.py
django_col/asgi.py
django_col/settings.py
django_col/urls.py
django_col/wsgi.py
django_col.egg-info/PKG-INFO
django_col.egg-info/SOURCES.txt
django_col.egg-info/dependency_links.txt
django_col.egg-info/not-zip-safe
django_col.egg-info/requires.txt
django_col.egg-info/top_level.txt