Metadata-Version: 1.0
Name: django-col
Version: 0.0.1
Summary: Django app using colours_library
Home-page: https://gitlab.bitcomp.intra/eryk_malczyk/django_col
Author: ErykMalczyk
Author-email: eryk.malczyk@bitcomp.fi
License: some_license
Platform: UNKNOWN
